kauri/__init__.py
kauri/bseries.py
kauri/display.py
kauri/generic_algebra.py
kauri/gentrees.py
kauri/maps.py
kauri/rk.py
kauri/rk_methods.py
kauri/trees.py
kauri/utils.py
kauri/bck/__init__.py
kauri/bck/bck.py
kauri/bck_impl/__init__.py
kauri/bck_impl/bck_impl.py
kauri/cem/__init__.py
kauri/cem/cem.py
kauri/cem_impl/__init__.py
kauri/cem_impl/cem_impl.py
kauri-1.0.0.dist-info/licenses/LICENSE
kauri-1.0.0.dist-info/METADATA
kauri-1.0.0.dist-info/WHEEL
kauri-1.0.0.dist-info/top_level.txt
kauri-1.0.0.dist-info/RECORD
